[
  {
    "Language": "English",
    "Speakers": 6925405,
    "Colour": "#bdbdbd"
  },
  {
    "Language": "French",
    "Speakers": 534255,
    "Colour": "#99c7ff"
  },
  {
    "Language": "Bosnian",
    "Speakers": 8605,
    "Colour": "#002F6C"
  },
  {
    "Language": "Croatian",
    "Speakers": 32770,
    "Colour": "#ff0000"
  },
  {
    "Language": "Dari",
    "Speakers": 37860,
    "Colour": "#007A36"
  },
  {
    "Language": "Iranian Persian",
    "Speakers": 103890,
    "Colour": "#239F40"
  },
  {
    "Language": "Odia",
    "Speakers": 1285,
    "Colour": "#8576b3"
  },
  {
    "Language": "Oriya, n.o.s.",
    "Speakers": 1015,
    "Colour": "#000000"
  },
  {
    "Language": "Persian (Farsi), n.o.s.",
    "Speakers": 13945,
    "Colour": "#000000"
  },
  {
    "Language": "Serbian",
    "Speakers": 37800,
    "Colour": "#6A0080"
  },
  {
    "Language": "Serbo-Croatian, n.i.e.",
    "Speakers": 1220,
    "Colour": "#000000"
  },
  {
    "Language": "Afrikaans",
    "Speakers": 5680,
    "Colour": "#FFB81C"
  },
  {
    "Language": "Aramaic, n.o.s.",
    "Speakers": 1165,
    "Colour": "#000000"
  },
  {
    "Language": "Assamese",
    "Speakers": 610,
    "Colour": "#000000"
  },
  {
    "Language": "Assyrian Neo-Aramaic",
    "Speakers": 16545,
    "Colour": "#945cd4"
  },
  {
    "Language": "Baluchi",
    "Speakers": 435,
    "Colour": "#000000"
  },
  {
    "Language": "Belarusian",
    "Speakers": 1145,
    "Colour": "#D22730"
  },
  {
    "Language": "Bengali",
    "Speakers": 64590,
    "Colour": "#006A4E"
  },
  {
    "Language": "Bulgarian",
    "Speakers": 8680,
    "Colour": "#00966E"
  },
  {
    "Language": "Chaldean Neo-Aramaic",
    "Speakers": 4850,
    "Colour": "#6FC7EA"
  },
  {
    "Language": "Czech",
    "Speakers": 7605,
    "Colour": "#11457E"
  },
  {
    "Language": "Danish",
    "Speakers": 2395,
    "Colour": "#C8102E"
  },
  {
    "Language": "Dutch",
    "Speakers": 15015,
    "Colour": "#fc5d00"
  },
  {
    "Language": "German",
    "Speakers": 60370,
    "Colour": "#DD0000"
  },
  {
    "Language": "Gujarati",
    "Speakers": 114565,
    "Colour": "#e02000"
  },
  {
    "Language": "Hindi",
    "Speakers": 353450,
    "Colour": "#FF671F"
  },
  {
    "Language": "Icelandic",
    "Speakers": 180,
    "Colour": "#000000"
  },
  {
    "Language": "Indo-Aryan languages, n.i.e.",
    "Speakers": 4855,
    "Colour": "#000000"
  },
  {
    "Language": "Kacchi",
    "Speakers": 7165,
    "Colour": "#004226"
  },
  {
    "Language": "Karenic languages, n.i.e.",
    "Speakers": 120,
    "Colour": "#000000"
  },
  {
    "Language": "Kashmiri",
    "Speakers": 940,
    "Colour": "#000000"
  },
  {
    "Language": "Konkani",
    "Speakers": 5930,
    "Colour": "#0b72cf"
  },
  {
    "Language": "Kurdish",
    "Speakers": 7785,
    "Colour": "#FEBD11"
  },
  {
    "Language": "Latvian",
    "Speakers": 2805,
    "Colour": "#A4343A"
  },
  {
    "Language": "Lithuanian",
    "Speakers": 3850,
    "Colour": "#046A38"
  },
  {
    "Language": "Low German, n.o.s.",
    "Speakers": 20,
    "Colour": "#000000"
  },
  {
    "Language": "Low Saxon",
    "Speakers": 0,
    "Colour": "#000000"
  },
  {
    "Language": "Macedonian",
    "Speakers": 17755,
    "Colour": "#D82126"
  },
  {
    "Language": "Marathi",
    "Speakers": 20790,
    "Colour": "#ff9700"
  },
  {
    "Language": "Nepali",
    "Speakers": 10360,
    "Colour": "#DC143C"
  },
  {
    "Language": "Norwegian",
    "Speakers": 1140,
    "Colour": "#BA0C2F"
  },
  {
    "Language": "Parsi",
    "Speakers": 450,
    "Colour": "#000000"
  },
  {
    "Language": "Pashto",
    "Speakers": 15525,
    "Colour": "#D32011"
  },
  {
    "Language": "Pennsylvania German",
    "Speakers": 0,
    "Colour": "#000000"
  },
  {
    "Language": "Plautdietsch",
    "Speakers": 145,
    "Colour": "#000000"
  },
  {
    "Language": "Polish",
    "Speakers": 88675,
    "Colour": "#DC143C"
  },
  {
    "Language": "Punjabi (Panjabi)",
    "Speakers": 332765,
    "Colour": "#8DBF2E"
  },
  {
    "Language": "Rohingya",
    "Speakers": 40,
    "Colour": "#000000"
  },
  {
    "Language": "Russian",
    "Speakers": 121255,
    "Colour": "#1C3578"
  },
  {
    "Language": "Rusyn",
    "Speakers": 95,
    "Colour": "#000000"
  },
  {
    "Language": "S'gaw Karen",
    "Speakers": 490,
    "Colour": "#000000"
  },
  {
    "Language": "Sindhi",
    "Speakers": 4910,
    "Colour": "#d8edcb"
  },
  {
    "Language": "Sinhala (Sinhalese)",
    "Speakers": 17655,
    "Colour": "#8D153A"
  },
  {
    "Language": "Slavic languages, n.i.e.",
    "Speakers": 235,
    "Colour": "#000000"
  },
  {
    "Language": "Slovak",
    "Speakers": 6760,
    "Colour": "#94219b"
  },
  {
    "Language": "Slovene (Slovenian)",
    "Speakers": 5110,
    "Colour": "#3bb3aa"
  },
  {
    "Language": "Swedish",
    "Speakers": 3020,
    "Colour": "#006AA7"
  },
  {
    "Language": "Swiss German",
    "Speakers": 1085,
    "Colour": "#000000"
  },
  {
    "Language": "Ukrainian",
    "Speakers": 43105,
    "Colour": "#0057B7"
  },
  {
    "Language": "Urdu",
    "Speakers": 248415,
    "Colour": "#115740"
  },
  {
    "Language": "Vlaams (Flemish)",
    "Speakers": 470,
    "Colour": "#000000"
  },
  {
    "Language": "Yiddish",
    "Speakers": 5480,
    "Colour": "#005EB8"
  },
  {
    "Language": "Amharic",
    "Speakers": 15695,
    "Colour": "#078930"
  },
  {
    "Language": "Anicinabemowin (Algonquin)",
    "Speakers": 10,
    "Colour": "#000000"
  },
  {
    "Language": "Arabic",
    "Speakers": 189785,
    "Colour": "#007A3D"
  },
  {
    "Language": "Atikamekw",
    "Speakers": 0,
    "Colour": "#000000"
  },
  {
    "Language": "Berber languages, n.i.e.",
    "Speakers": 105,
    "Colour": "#000000"
  },
  {
    "Language": "Bilen",
    "Speakers": 190,
    "Colour": "#000000"
  },
  {
    "Language": "Burmese",
    "Speakers": 1490,
    "Colour": "#000000"
  },
  {
    "Language": "Catalan",
    "Speakers": 445,
    "Colour": "#000000"
  },
  {
    "Language": "Celtic languages, n.i.e.",
    "Speakers": 185,
    "Colour": "#000000"
  },
  {
    "Language": "Chinese languages, n.i.e.",
    "Speakers": 365,
    "Colour": "#000000"
  },
  {
    "Language": "Chinese, n.o.s.",
    "Speakers": 3925,
    "Colour": "#000000"
  },
  {
    "Language": "Cree languages",
    "Speakers": 230,
    "Colour": "#000000"
  },
  {
    "Language": "Cushitic languages, n.i.e.",
    "Speakers": 225,
    "Colour": "#000000"
  },
  {
    "Language": "Dakelh (Carrier)",
    "Speakers": 0,
    "Colour": "#000000"
  },
  {
    "Language": "Dane-zaa (Beaver)",
    "Speakers": 0,
    "Colour": "#000000"
  },
  {
    "Language": "Dene, n.o.s.",
    "Speakers": 15,
    "Colour": "#000000"
  },
  {
    "Language": "Frisian",
    "Speakers": 435,
    "Colour": "#000000"
  },
  {
    "Language": "Gwich'in",
    "Speakers": 0,
    "Colour": "#000000"
  },
  {
    "Language": "Hakka",
    "Speakers": 8290,
    "Colour": "#000095"
  },
  {
    "Language": "Harari",
    "Speakers": 1440,
    "Colour": "#DA121A"
  },
  {
    "Language": "Hausa",
    "Speakers": 1340,
    "Colour": "#1B7339"
  },
  {
    "Language": "Hebrew",
    "Speakers": 41580,
    "Colour": "#005EB8"
  },
  {
    "Language": "Indo-Iranian languages, n.i.e.",
    "Speakers": 1070,
    "Colour": "#000000"
  },
  {
    "Language": "Innu (Montagnais)",
    "Speakers": 0,
    "Colour": "#000000"
  },
  {
    "Language": "Irish",
    "Speakers": 1350,
    "Colour": "#009A44"
  },
  {
    "Language": "Italian",
    "Speakers": 226005,
    "Colour": "#007FA3"
  },
  {
    "Language": "Italic (Romance) languages, n.i.e.",
    "Speakers": 1385,
    "Colour": "#000000"
  },
  {
    "Language": "Kabyle",
    "Speakers": 330,
    "Colour": "#000000"
  },
  {
    "Language": "Kuki-Chin languages",
    "Speakers": 55,
    "Colour": "#000000"
  },
  {
    "Language": "Malagasy, n.o.s.",
    "Speakers": 70,
    "Colour": "#000000"
  },
  {
    "Language": "Maltese",
    "Speakers": 4510,
    "Colour": "#C01B22"
  },
  {
    "Language": "Mandarin",
    "Speakers": 391545,
    "Colour": "#DC4633"
  },
  {
    "Language": "Merina",
    "Speakers": 10,
    "Colour": "#000000"
  },
  {
    "Language": "Mi'kmaq",
    "Speakers": 95,
    "Colour": "#000000"
  },
  {
    "Language": "Min Dong",
    "Speakers": 1305,
    "Colour": "#002864"
  },
  {
    "Language": "Min Nan (Chaochow, Teochow, Fukien, Taiwanese)",
    "Speakers": 15485,
    "Colour": "#DC0000"
  },
  {
    "Language": "Mina",
    "Speakers": 70,
    "Colour": "#000000"
  },
  {
    "Language": "Naskapi",
    "Speakers": 0,
    "Colour": "#000000"
  },
  {
    "Language": "Oji-Cree",
    "Speakers": 15,
    "Colour": "#000000"
  },
  {
    "Language": "Ojibway languages",
    "Speakers": 715,
    "Colour": "#000000"
  },
  {
    "Language": "Oromo",
    "Speakers": 2215,
    "Colour": "#0645B1"
  },
  {
    "Language": "Portuguese",
    "Speakers": 148960,
    "Colour": "#E42518"
  },
  {
    "Language": "Romanian",
    "Speakers": 30770,
    "Colour": "#002B7F"
  },
  {
    "Language": "Scottish Gaelic",
    "Speakers": 300,
    "Colour": "#000000"
  },
  {
    "Language": "Semitic languages, n.i.e.",
    "Speakers": 375,
    "Colour": "#000000"
  },
  {
    "Language": "Slavey-Hare languages",
    "Speakers": 0,
    "Colour": "#000000"
  },
  {
    "Language": "Somali",
    "Speakers": 17520,
    "Colour": "#4189DD"
  },
  {
    "Language": "Spanish",
    "Speakers": 241520,
    "Colour": "#F1C500"
  },
  {
    "Language": "Tahltan languages",
    "Speakers": 0,
    "Colour": "#000000"
  },
  {
    "Language": "Tamazight",
    "Speakers": 190,
    "Colour": "#000000"
  },
  {
    "Language": "Tibetan",
    "Speakers": 7225,
    "Colour": "#29166F"
  },
  {
    "Language": "Tibeto-Burman languages, n.i.e.",
    "Speakers": 655,
    "Colour": "#000000"
  },
  {
    "Language": "Tigrigna",
    "Speakers": 10715,
    "Colour": "#E4002B"
  },
  {
    "Language": "Tlicho (Dogrib)",
    "Speakers": 0,
    "Colour": "#000000"
  },
  {
    "Language": "Tse'khene (Sekani)",
    "Speakers": 0,
    "Colour": "#000000"
  },
  {
    "Language": "Tsilhqot'in (Chilcotin)",
    "Speakers": 0,
    "Colour": "#000000"
  },
  {
    "Language": "Tsuu T'ina (Sarsi)",
    "Speakers": 0,
    "Colour": "#000000"
  },
  {
    "Language": "Tutchone languages",
    "Speakers": 0,
    "Colour": "#000000"
  },
  {
    "Language": "Welsh",
    "Speakers": 325,
    "Colour": "#000000"
  },
  {
    "Language": "Wetsuwet'en-Babine",
    "Speakers": 0,
    "Colour": "#000000"
  },
  {
    "Language": "Wolastoqewi (Malecite)",
    "Speakers": 0,
    "Colour": "#000000"
  },
  {
    "Language": "Wu (Shanghainese)",
    "Speakers": 5770,
    "Colour": "#6c3bb1"
  },
  {
    "Language": "Yue (Cantonese)",
    "Speakers": 320285,
    "Colour": "#077662"
  },
  {
    "Language": "African, n.o.s.",
    "Speakers": 480,
    "Colour": "#000000"
  },
  {
    "Language": "Akan (Twi)",
    "Speakers": 14715,
    "Colour": "#009739"
  },
  {
    "Language": "Albanian",
    "Speakers": 20125,
    "Colour": "#DA291C"
  },
  {
    "Language": "Algonquian languages, n.i.e.",
    "Speakers": 0,
    "Colour": "#000000"
  },
  {
    "Language": "American Sign Language",
    "Speakers": 6875,
    "Colour": "#00A189"
  },
  {
    "Language": "Armenian",
    "Speakers": 16525,
    "Colour": "#FF9E1B"
  },
  {
    "Language": "Assiniboine",
    "Speakers": 0,
    "Colour": "#000000"
  },
  {
    "Language": "Athabaskan languages, n.i.e.",
    "Speakers": 0,
    "Colour": "#000000"
  },
  {
    "Language": "Austro-Asiatic languages, n.i.e",
    "Speakers": 155,
    "Colour": "#000000"
  },
  {
    "Language": "Austronesian languages, n.i.e.",
    "Speakers": 5175,
    "Colour": "#000000"
  },
  {
    "Language": "Azerbaijani",
    "Speakers": 4860,
    "Colour": "#00AF66"
  },
  {
    "Language": "Bamanankan",
    "Speakers": 350,
    "Colour": "#000000"
  },
  {
    "Language": "Bikol",
    "Speakers": 1155,
    "Colour": "#000000"
  },
  {
    "Language": "Bisaya, n.o.s.",
    "Speakers": 2660,
    "Colour": "#000000"
  },
  {
    "Language": "Blackfoot",
    "Speakers": 0,
    "Colour": "#000000"
  },
  {
    "Language": "Cayuga",
    "Speakers": 45,
    "Colour": "#000000"
  },
  {
    "Language": "Cebuano",
    "Speakers": 8170,
    "Colour": "#d1ab00"
  },
  {
    "Language": "Coptic",
    "Speakers": 1700,
    "Colour": "#C09300"
  },
  {
    "Language": "Creole languages, n.i.e.",
    "Speakers": 2835,
    "Colour": "#000000"
  },
  {
    "Language": "Creole, n.o.s.",
    "Speakers": 7235,
    "Colour": "#000000"
  },
  {
    "Language": "Dakota",
    "Speakers": 0,
    "Colour": "#000000"
  },
  {
    "Language": "Dinka",
    "Speakers": 55,
    "Colour": "#000000"
  },
  {
    "Language": "Dravidian languages, n.i.e.",
    "Speakers": 0,
    "Colour": "#000000"
  },
  {
    "Language": "Edo",
    "Speakers": 2650,
    "Colour": "#005000"
  },
  {
    "Language": "Estonian",
    "Speakers": 2645,
    "Colour": "#0072CE"
  },
  {
    "Language": "Fijian",
    "Speakers": 160,
    "Colour": "#000000"
  },
  {
    "Language": "Finnish",
    "Speakers": 2855,
    "Colour": "#002F6C"
  },
  {
    "Language": "Fulah (Pular, Pulaar, Fulfulde)",
    "Speakers": 525,
    "Colour": "#000000"
  },
  {
    "Language": "Ga",
    "Speakers": 1395,
    "Colour": "#EF3340"
  },
  {
    "Language": "Ganda",
    "Speakers": 1990,
    "Colour": "#D90000"
  },
  {
    "Language": "Gikuyu",
    "Speakers": 765,
    "Colour": "#000000"
  },
  {
    "Language": "Gitxsan (Gitksan)",
    "Speakers": 0,
    "Colour": "#000000"
  },
  {
    "Language": "Greek",
    "Speakers": 60155,
    "Colour": "#001489"
  },
  {
    "Language": "Haisla",
    "Speakers": 0,
    "Colour": "#000000"
  },
  {
    "Language": "Haitian Creole",
    "Speakers": 3610,
    "Colour": "#D21034"
  },
  {
    "Language": "Halkomelem",
    "Speakers": 0,
    "Colour": "#000000"
  },
  {
    "Language": "Heiltsuk",
    "Speakers": 0,
    "Colour": "#000000"
  },
  {
    "Language": "Hiligaynon",
    "Speakers": 5260,
    "Colour": "#b33000"
  },
  {
    "Language": "Hungarian",
    "Speakers": 23175,
    "Colour": "#477050"
  },
  {
    "Language": "Igbo",
    "Speakers": 5335,
    "Colour": "#e48cc6"
  },
  {
    "Language": "Ilocano",
    "Speakers": 22440,
    "Colour": "#17643a"
  },
  {
    "Language": "Indonesian",
    "Speakers": 5925,
    "Colour": "#ff0000"
  },
  {
    "Language": "Inuinnaqtun (Inuvialuktun)",
    "Speakers": 20,
    "Colour": "#000000"
  },
  {
    "Language": "Inuktitut",
    "Speakers": 85,
    "Colour": "#000000"
  },
  {
    "Language": "Inuktut (Inuit) languages, n.i.e.",
    "Speakers": 0,
    "Colour": "#000000"
  },
  {
    "Language": "Iroquoian languages, n.i.e.",
    "Speakers": 10,
    "Colour": "#000000"
  },
  {
    "Language": "Jamaican English Creole",
    "Speakers": 2630,
    "Colour": "#009B3A"
  },
  {
    "Language": "Kankanaey",
    "Speakers": 465,
    "Colour": "#000000"
  },
  {
    "Language": "Kannada",
    "Speakers": 10525,
    "Colour": "#ff0000"
  },
  {
    "Language": "Kazakh",
    "Speakers": 475,
    "Colour": "#000000"
  },
  {
    "Language": "Khmer (Cambodian)",
    "Speakers": 4965,
    "Colour": "#032EA1"
  },
  {
    "Language": "Kinaray-a",
    "Speakers": 235,
    "Colour": "#000000"
  },
  {
    "Language": "Kinyarwanda (Rwanda)",
    "Speakers": 1210,
    "Colour": "#000000"
  },
  {
    "Language": "Krio",
    "Speakers": 400,
    "Colour": "#000000"
  },
  {
    "Language": "Kwak'wala (Kwakiutl)",
    "Speakers": 0,
    "Colour": "#000000"
  },
  {
    "Language": "Lao",
    "Speakers": 3685,
    "Colour": "#CE1126"
  },
  {
    "Language": "Lillooet",
    "Speakers": 0,
    "Colour": "#000000"
  },
  {
    "Language": "Lingala",
    "Speakers": 3285,
    "Colour": "#0085CA"
  },
  {
    "Language": "Luba-Kasai",
    "Speakers": 385,
    "Colour": "#000000"
  },
  {
    "Language": "Malay",
    "Speakers": 3380,
    "Colour": "#0032A0"
  },
  {
    "Language": "Malayalam",
    "Speakers": 32010,
    "Colour": "#CC0000"
  },
  {
    "Language": "Mohawk",
    "Speakers": 155,
    "Colour": "#000000"
  },
  {
    "Language": "Morisyen",
    "Speakers": 4580,
    "Colour": "#00A551"
  },
  {
    "Language": "Mwani",
    "Speakers": 395,
    "Colour": "#000000"
  },
  {
    "Language": "Mòoré",
    "Speakers": 40,
    "Colour": "#000000"
  },
  {
    "Language": "Ndebele",
    "Speakers": 550,
    "Colour": "#000000"
  },
  {
    "Language": "Niger-Congo languages, n.i.e.",
    "Speakers": 7415,
    "Colour": "#000000"
  },
  {
    "Language": "Nilo-Saharan languages, n.i.e.",
    "Speakers": 1060,
    "Colour": "#000000"
  },
  {
    "Language": "Nisga'a",
    "Speakers": 0,
    "Colour": "#000000"
  },
  {
    "Language": "Ntlakapamux (Thompson)",
    "Speakers": 0,
    "Colour": "#000000"
  },
  {
    "Language": "Nuer",
    "Speakers": 45,
    "Colour": "#000000"
  },
  {
    "Language": "Nuu-chah-nulth (Nootka)",
    "Speakers": 0,
    "Colour": "#000000"
  },
  {
    "Language": "Oneida",
    "Speakers": 0,
    "Colour": "#000000"
  },
  {
    "Language": "Pampangan (Kapampangan, Pampango)",
    "Speakers": 2985,
    "Colour": "#AB1368"
  },
  {
    "Language": "Pangasinan",
    "Speakers": 1385,
    "Colour": "#000000"
  },
  {
    "Language": "Quebec Sign Language",
    "Speakers": 35,
    "Colour": "#000000"
  },
  {
    "Language": "Rundi (Kirundi)",
    "Speakers": 1015,
    "Colour": "#1EB53A"
  },
  {
    "Language": "Salish languages, n.i.e.",
    "Speakers": 0,
    "Colour": "#000000"
  },
  {
    "Language": "Sango",
    "Speakers": 85,
    "Colour": "#000000"
  },
  {
    "Language": "Secwepemctsin (Shuswap)",
    "Speakers": 0,
    "Colour": "#000000"
  },
  {
    "Language": "Shona",
    "Speakers": 1825,
    "Colour": "#009739"
  },
  {
    "Language": "Sign languages, n.i.e.",
    "Speakers": 1060,
    "Colour": "#000000"
  },
  {
    "Language": "Sino-Tibetan languages, n.i.e.",
    "Speakers": 335,
    "Colour": "#000000"
  },
  {
    "Language": "Siouan languages, n.i.e.",
    "Speakers": 0,
    "Colour": "#000000"
  },
  {
    "Language": "Soninke",
    "Speakers": 265,
    "Colour": "#000000"
  },
  {
    "Language": "Sotho-Tswana languages",
    "Speakers": 455,
    "Colour": "#000000"
  },
  {
    "Language": "Squamish",
    "Speakers": 0,
    "Colour": "#000000"
  },
  {
    "Language": "Stoney",
    "Speakers": 0,
    "Colour": "#000000"
  },
  {
    "Language": "Straits",
    "Speakers": 0,
    "Colour": "#000000"
  },
  {
    "Language": "Swahili",
    "Speakers": 14825,
    "Colour": "#00A3DD"
  },
  {
    "Language": "Syilx (Okanagan)",
    "Speakers": 0,
    "Colour": "#000000"
  },
  {
    "Language": "Tagalog (Pilipino, Filipino)",
    "Speakers": 228395,
    "Colour": "#BF0D3E"
  },
  {
    "Language": "Tai-Kadai languages, n.i.e.",
    "Speakers": 285,
    "Colour": "#000000"
  },
  {
    "Language": "Tamil",
    "Speakers": 175890,
    "Colour": "#EB7400"
  },
  {
    "Language": "Telugu",
    "Speakers": 30530,
    "Colour": "#106827"
  },
  {
    "Language": "Thai",
    "Speakers": 3510,
    "Colour": "#00247D"
  },
  {
    "Language": "Tlingit",
    "Speakers": 10,
    "Colour": "#000000"
  },
  {
    "Language": "Tsimshian",
    "Speakers": 0,
    "Colour": "#000000"
  },
  {
    "Language": "Tulu",
    "Speakers": 1065,
    "Colour": "#d276fa"
  },
  {
    "Language": "Turkic languages, n.i.e.",
    "Speakers": 790,
    "Colour": "#000000"
  },
  {
    "Language": "Turkish",
    "Speakers": 33065,
    "Colour": "#C8102E"
  },
  {
    "Language": "Uyghur",
    "Speakers": 510,
    "Colour": "#000000"
  },
  {
    "Language": "Uzbek",
    "Speakers": 1190,
    "Colour": "#000000"
  },
  {
    "Language": "Vietnamese",
    "Speakers": 77355,
    "Colour": "#C8102E"
  },
  {
    "Language": "Wakashan languages, n.i.e.",
    "Speakers": 0,
    "Colour": "#000000"
  },
  {
    "Language": "Waray-Waray",
    "Speakers": 1445,
    "Colour": "#000000"
  },
  {
    "Language": "Wojenaka",
    "Speakers": 90,
    "Colour": "#000000"
  },
  {
    "Language": "Wolof",
    "Speakers": 735,
    "Colour": "#000000"
  },
  {
    "Language": "Yoruba",
    "Speakers": 17215,
    "Colour": "#006A4A"
  },
  {
    "Language": "Éwé",
    "Speakers": 785,
    "Colour": "#000000"
  },
  {
    "Language": "Georgian",
    "Speakers": 1935,
    "Colour": "#DA291C"
  },
  {
    "Language": "Haida",
    "Speakers": 0,
    "Colour": "#000000"
  },
  {
    "Language": "Hmong-Mien languages",
    "Speakers": 30,
    "Colour": "#000000"
  },
  {
    "Language": "Indigenous languages, n.i.e.",
    "Speakers": 25,
    "Colour": "#000000"
  },
  {
    "Language": "Indigenous languages, n.o.s.",
    "Speakers": 35,
    "Colour": "#000000"
  },
  {
    "Language": "Japanese",
    "Speakers": 22135,
    "Colour": "#BC002D"
  },
  {
    "Language": "Korean",
    "Speakers": 71745,
    "Colour": "#0F64CD"
  },
  {
    "Language": "Ktunaxa (Kutenai)",
    "Speakers": 0,
    "Colour": "#000000"
  },
  {
    "Language": "Michif",
    "Speakers": 10,
    "Colour": "#000000"
  },
  {
    "Language": "Mongolian",
    "Speakers": 580,
    "Colour": "#000000"
  },
  {
    "Language": "Other",
    "Speakers": "",
    "Colour": "#5c5c5c"
  }
]